{
  "schemaVersion": 1,
  "id": "flatworld",
  "version": "${version}",
  "name": "FlatWorld",
  "description": "Flat world generation with new ways to obtain resources",
  "authors": [
    "jsorrell",
    "53-Technical-support-group"
  ],
  "contact": {
    "sources": "https://github.com/53-Technical-support-group/CarpetFlatAdditions",
    "issues": "https://github.com/53-Technical-support-group/CarpetFlatAdditions/issues"
  },
  "license": "MIT",
  "environment": "*",
  "entrypoints": {
    "main": [
      "dev.dubhe.flatworld.FlatWorldExtension"
    ],
    "client": [
      "dev.dubhe.flatworld.FlatWorldClient"
    ]
  },
  "mixins": [
    "flatworld.mixins.json"
  ],
  "accessWidener": "flatworld.accesswidener",
  "depends": {
    "fabricloader": "*",
    "fabric": "*",
    "minecraft": ">=1.18.2 <1.19",
    "carpet": "*"
  }
}
